d2l/__init__.py
d2l/torch.py
j_py/__init__.py
j_py/basic.py
jspider/JProxy.py
jspider/JTime.py
jspider/__init__.py
jspider/net.py
jspider/parse.py
tree/ListNode.py
tree/TreeNode.py
tree/__init__.py
jshen-0.0.20.dist-info/LICENSE
jshen-0.0.20.dist-info/METADATA
jshen-0.0.20.dist-info/WHEEL
jshen-0.0.20.dist-info/top_level.txt
jshen-0.0.20.dist-info/RECORD
