Metadata-Version: 2.1
Name: jshen
Version: 0.0.20
Summary: Tools for leetcode,kaggle...
Home-page: https://github.com/JieShenAI/jshen/
Author: J.Shen
Author-email: shenjiecn@qq.com
License: MIT
Keywords: TreeNode
Platform: any
Classifier: Development Status :: 3 - Alpha
Classifier: Intended Audience :: Developers
Classifier: Topic :: Software Development :: Build Tools
Classifier: License :: OSI Approved :: MIT License
Classifier: Programming Language :: Python :: 3
Classifier: Programming Language :: Python :: 3.4
Classifier: Programming Language :: Python :: 3.5
Classifier: Programming Language :: Python :: 3.6
License-File: LICENSE
